JAK/Application.py
JAK/DevTools.py
JAK/IPC.py
JAK/KeyBindings.py
JAK/RequestInterceptor.py
JAK/Settings.py
JAK/Utils.py
JAK/WebEngine.py
JAK/Widgets.py
JAK/__init__.py
usr/bin/jak-cli
Jade_Application_Kit-3.5.6.dist-info/LICENSE
Jade_Application_Kit-3.5.6.dist-info/METADATA
Jade_Application_Kit-3.5.6.dist-info/WHEEL
Jade_Application_Kit-3.5.6.dist-info/top_level.txt
Jade_Application_Kit-3.5.6.dist-info/RECORD
