Metadata-Version: 2.1
Name: Jade-Application-Kit
Version: 3.5.6
Summary: Create native web wrappers or write hybrid Desktop applications on Linux, with Python, JavaScript, HTML, and Blink
Home-page: https://codesardine.github.io/Jade-Application-Kit
Author: Vitor Lopes
License: GPL
Download-URL: https://github.com/codesardine/Jade-Application-Kit/zipball/master
Keywords: Jade Application Kit,gui,blink,html5,web technologies,javascript,python,webgl,CSS,QTWebEngine,linux,webview
Platform: UNKNOWN
Classifier: Development Status :: 4 - Beta
Classifier: Intended Audience :: Developers
Classifier: Intended Audience :: End Users/Desktop
Classifier: License :: OSI Approved :: GNU General Public License (GPL) 
Classifier: Operating System :: POSIX :: Linux
Classifier: Environment :: Web Environment
Classifier: Topic :: Desktop Environment
Classifier: Environment :: X11 Applications
Classifier: Programming Language :: Python :: 3.6
Classifier: Topic :: Software Development :: Libraries :: Application Frameworks
Classifier: Topic :: Software Development :: Libraries :: Python Modules
Classifier: Topic :: Software Development :: User Interfaces
Requires-Python: >=3.6
Requires-Dist: PySide2
Requires-Dist: PyQt5
